django_anysign/.__init__.py.un~
django_anysign/.api.py.un~
django_anysign/.apps.py.un~
django_anysign/.backend.py.un~
django_anysign/.models.py.un~
django_anysign/__init__.py
django_anysign/api.py
django_anysign/backend.py
django_anysign/loading.py
django_anysign/models.py
django_anysign/settings.py
django_anysign/utils/__init__.py
django_anysign/utils/importlib.py
django_dummysign/.backend.py.un~
django_dummysign/__init__.py
django_dummysign/backend.py
django_anysign-1.4.dist-info/AUTHORS
django_anysign-1.4.dist-info/LICENSE
django_anysign-1.4.dist-info/METADATA
django_anysign-1.4.dist-info/WHEEL
django_anysign-1.4.dist-info/top_level.txt
django_anysign-1.4.dist-info/RECORD
