Metadata-Version: 2.1
Name: django-anysign
Version: 1.4
Summary: Online signature for Django: multiple services, generic API.
Home-page: https://django-anysign.readthedocs.io/
Author: Benoît Bryon
Author-email: novafloss@people-doc.com
License: BSD
Keywords: signature sign signer generic
Platform: UNKNOWN
Classifier: Development Status :: 5 - Production/Stable
Classifier: License :: OSI Approved :: BSD License
Classifier: Programming Language :: Python :: 2
Classifier: Programming Language :: Python :: 2.7
Classifier: Programming Language :: Python :: 3
Classifier: Programming Language :: Python :: 3.5
Classifier: Programming Language :: Python :: 3.6
Classifier: Programming Language :: Python :: 3.7
Classifier: Framework :: Django
Classifier: Framework :: Django :: 1.11
Classifier: Framework :: Django :: 2.0
Classifier: Framework :: Django :: 2.1
Classifier: Framework :: Django :: 2.2
Requires-Dist: Django (>=1.11)
Requires-Dist: setuptools
Provides-Extra: test
Requires-Dist: tox ; extra == 'test'
